electrificationutils/__init__.py
electrificationutils/api/__init__.py
electrificationutils/api/ggrfhvac_update_api.py
electrificationutils/api/health_data_api.py
electrificationutils/api/health_impacts_api.py
electrificationutils/api/range_upgrade_api.py
electrificationutils/api_client.py
electrificationutils/api_response.py
electrificationutils/configuration.py
electrificationutils/exceptions.py
electrificationutils/models/__init__.py
electrificationutils/models/energy_quantity.py
electrificationutils/models/energy_tradeoff.py
electrificationutils/models/group_by.py
electrificationutils/models/http_validation_error.py
electrificationutils/models/hvac_efficiency_electric_detailed.py
electrificationutils/models/hvac_efficiency_fossil_fuels.py
electrificationutils/models/hvac_update_results.py
electrificationutils/models/metrics.py
electrificationutils/models/range_fuel_type.py
electrificationutils/models/upgrade_option.py
electrificationutils/models/validation_error.py
electrificationutils/models/validation_error_loc_inner.py
electrificationutils/py.typed
electrificationutils/rest.py
electrificationutils-0.3.4.dist-info/LICENSE.md
electrificationutils-0.3.4.dist-info/METADATA
electrificationutils-0.3.4.dist-info/WHEEL
electrificationutils-0.3.4.dist-info/RECORD
