Metadata-Version: 2.1
Name: electrificationutils
Version: 0.3.4
Summary: smallmodelsapi
Home-page: https://github.com/GIT_USER_ID/GIT_REPO_ID
License: NoLicense
Keywords: OpenAPI,OpenAPI-Generator,smallmodelsapi
Author: OpenAPI Generator Community
Author-email: team@openapitools.org
Requires-Python: >=3.8,<4.0
Classifier: License :: Other/Proprietary License
Classifier: Programming Language :: Python :: 3
Classifier: Programming Language :: Python :: 3.8
Classifier: Programming Language :: Python :: 3.9
Classifier: Programming Language :: Python :: 3.10
Classifier: Programming Language :: Python :: 3.11
Classifier: Programming Language :: Python :: 3.12
Requires-Dist: keyrings-google-artifactregistry-auth (>=1.1.2,<2.0.0)
Requires-Dist: pydantic (>=2)
Requires-Dist: python-dateutil (>=2.8.2)
Requires-Dist: typing-extensions (>=4.7.1)
Requires-Dist: urllib3 (>=1.25.3,<3.0.0)
Project-URL: Repository, https://github.com/GIT_USER_ID/GIT_REPO_ID
